LICENSE.txt
README.md
pyproject.toml
setup.cfg
setup.py
hui/ALLOWED_TAGS.py
hui/Generator.py
hui/ParserBase.py
hui/ParserPayload.py
hui/__init__.py
hui/generated_payloads.json
hui/identify.py
hui.egg-info/PKG-INFO
hui.egg-info/SOURCES.txt
hui.egg-info/dependency_links.txt
hui.egg-info/top_level.txt
hui/results_parsers/GO_BLUEMONDAY.json
hui/results_parsers/GO_HTML.json
hui/results_parsers/JAVA_JSOUP.json
hui/results_parsers/JSDOM_HTML.json
hui/results_parsers/JS_DOMPURIFY.json
hui/results_parsers/JS_HTMLPARSER2.json
hui/results_parsers/JS_SANITIZE_HTML.json
hui/results_parsers/PYTHON_HTML.json
hui/results_parsers/PYTHON_HTML_SANITIZE.json
hui/results_parsers/PYTHON_LXML_HTML.json